{"id":"Grid.js","dependencies":[{"name":"/Users/matthewshort/MatchThree/package.json","includedInParent":true,"mtime":1536441257151},{"name":"/Users/matthewshort/MatchThree/.babelrc","includedInParent":true,"mtime":1536441255938},{"name":"./constants","loc":{"line":1,"column":27},"parent":"/Users/matthewshort/MatchThree/src/Grid.js","resolved":"/Users/matthewshort/MatchThree/src/constants.js"},{"name":"./Cell","loc":{"line":3,"column":17},"parent":"/Users/matthewshort/MatchThree/src/Grid.js","resolved":"/Users/matthewshort/MatchThree/src/Cell.js"}],"generated":{"js":"'use strict';\n\nObject.defineProperty(exports, \"__esModule\", {\n  value: true\n});\n\nvar _createClass = function () { function defineProperties(target, props) { for (var i = 0; i < props.length; i++) { var descriptor = props[i]; descriptor.enumerable = descriptor.enumerable || false; descriptor.configurable = true; if (\"value\" in descriptor) descriptor.writable = true; Object.defineProperty(target, descriptor.key, descriptor); } } return function (Constructor, protoProps, staticProps) { if (protoProps) defineProperties(Constructor.prototype, protoProps); if (staticProps) defineProperties(Constructor, staticProps); return Constructor; }; }();\n\nvar _constants = require('./constants');\n\nvar _Cell = require('./Cell');\n\nvar _Cell2 = _interopRequireDefault(_Cell);\n\nfunction _interopRequireDefault(obj) { return obj && obj.__esModule ? obj : { default: obj }; }\n\nfunction _classCallCheck(instance, Constructor) { if (!(instance instanceof Constructor)) { throw new TypeError(\"Cannot call a class as a function\"); } }\n\nvar Grid = function () {\n  function Grid() {\n    _classCallCheck(this, Grid);\n\n    this.rows = this._buildRows(_constants.BOARD_SIZE);\n    this.el = this._buildEl();\n  }\n\n  _createClass(Grid, [{\n    key: '_buildEl',\n    value: function _buildEl() {\n      var el = document.createElement('div');\n    }\n  }, {\n    key: '_buildRows',\n    value: function _buildRows(size) {\n      var rows = [];\n\n      for (var i = 0; i < size; i++) {\n        var row = [];\n\n        for (var j = 0; j < size; j++) {\n          row.push(_Cell2.default.random());\n        }\n\n        rows.push(row);\n      }\n\n      return rows;\n    }\n  }, {\n    key: '_getCell',\n    value: function _getCell(pos) {\n      return this.rows[pos.row][pos.col];\n    }\n  }, {\n    key: '_setCell',\n    value: function _setCell(pos, cell) {\n      this.rows[pos.row][pos.col] = cell;\n    }\n  }, {\n    key: 'swapCells',\n    value: function swapCells(posOne, posTwo) {\n      var cellOne = this._getCell(posOne);\n      this._setCell(posOne, this._getCell(posTwo));\n      this._setCell(posTwo, cellOne);\n    }\n  }, {\n    key: 'getEl',\n    value: function getEl() {\n      var gridEl = document.createElement('div');\n      gridEl.classList.add('grid');\n\n      this.rows.forEach(function (row) {\n        var rowEl = document.createElement('div');\n        rowEl.classList.add('row');\n\n        row.forEach(function (cell) {\n          rowEl.appendChild(cell.getEl());\n        });\n\n        gridEl.appendChild(rowEl);\n      });\n\n      return gridEl;\n    }\n  }]);\n\n  return Grid;\n}();\n\nexports.default = Grid;","map":{"mappings":[{"generated":{"line":9,"column":0},"source":"Grid.js","original":{"line":1,"column":0}},{"generated":{"line":11,"column":0},"source":"Grid.js","original":{"line":3,"column":0}},{"name":"Grid","generated":{"line":19,"column":4},"source":"Grid.js","original":{"line":5,"column":6}},{"generated":{"line":20,"column":0},"source":"Grid.js","original":{"line":6,"column":2}},{"generated":{"line":20,"column":18},"source":"Grid.js","original":{"line":6,"column":16}},{"generated":{"line":21,"column":0},"source":"Grid.js","original":{"line":6,"column":16}},{"generated":{"line":23,"column":0},"source":"Grid.js","original":{"line":7,"column":4}},{"name":"rows","generated":{"line":23,"column":9},"source":"Grid.js","original":{"line":7,"column":9}},{"generated":{"line":23,"column":13},"source":"Grid.js","original":{"line":7,"column":4}},{"generated":{"line":23,"column":16},"source":"Grid.js","original":{"line":7,"column":16}},{"name":"_buildRows","generated":{"line":23,"column":21},"source":"Grid.js","original":{"line":7,"column":21}},{"generated":{"line":23,"column":31},"source":"Grid.js","original":{"line":7,"column":16}},{"name":"BOARD_SIZE","generated":{"line":23,"column":32},"source":"Grid.js","original":{"line":7,"column":32}},{"generated":{"line":23,"column":53},"source":"Grid.js","original":{"line":7,"column":16}},{"generated":{"line":23,"column":54},"source":"Grid.js","original":{"line":7,"column":4}},{"generated":{"line":24,"column":0},"source":"Grid.js","original":{"line":8,"column":4}},{"name":"el","generated":{"line":24,"column":9},"source":"Grid.js","original":{"line":8,"column":9}},{"generated":{"line":24,"column":11},"source":"Grid.js","original":{"line":8,"column":4}},{"generated":{"line":24,"column":14},"source":"Grid.js","original":{"line":8,"column":14}},{"name":"_buildEl","generated":{"line":24,"column":19},"source":"Grid.js","original":{"line":8,"column":19}},{"generated":{"line":24,"column":27},"source":"Grid.js","original":{"line":8,"column":14}},{"generated":{"line":24,"column":29},"source":"Grid.js","original":{"line":8,"column":4}},{"generated":{"line":25,"column":0},"source":"Grid.js","original":{"line":9,"column":3}},{"generated":{"line":29,"column":31},"source":"Grid.js","original":{"line":11,"column":13}},{"generated":{"line":30,"column":0},"source":"Grid.js","original":{"line":12,"column":4}},{"name":"el","generated":{"line":30,"column":10},"source":"Grid.js","original":{"line":12,"column":10}},{"name":"document","generated":{"line":30,"column":15},"source":"Grid.js","original":{"line":12,"column":15}},{"name":"createElement","generated":{"line":30,"column":24},"source":"Grid.js","original":{"line":12,"column":24}},{"generated":{"line":30,"column":37},"source":"Grid.js","original":{"line":12,"column":15}},{"generated":{"line":30,"column":38},"source":"Grid.js","original":{"line":12,"column":38}},{"generated":{"line":30,"column":43},"source":"Grid.js","original":{"line":12,"column":15}},{"generated":{"line":30,"column":44},"source":"Grid.js","original":{"line":12,"column":4}},{"generated":{"line":31,"column":0},"source":"Grid.js","original":{"line":13,"column":3}},{"name":"size","generated":{"line":34,"column":31},"source":"Grid.js","original":{"line":15,"column":13}},{"generated":{"line":34,"column":37},"source":"Grid.js","original":{"line":15,"column":19}},{"generated":{"line":35,"column":0},"source":"Grid.js","original":{"line":16,"column":4}},{"name":"rows","generated":{"line":35,"column":10},"source":"Grid.js","original":{"line":16,"column":10}},{"generated":{"line":35,"column":17},"source":"Grid.js","original":{"line":16,"column":17}},{"generated":{"line":35,"column":19},"source":"Grid.js","original":{"line":16,"column":4}},{"generated":{"line":37,"column":0},"source":"Grid.js","original":{"line":18,"column":4}},{"generated":{"line":37,"column":11},"source":"Grid.js","original":{"line":18,"column":9}},{"name":"i","generated":{"line":37,"column":15},"source":"Grid.js","original":{"line":18,"column":13}},{"generated":{"line":37,"column":19},"source":"Grid.js","original":{"line":18,"column":17}},{"generated":{"line":37,"column":20},"source":"Grid.js","original":{"line":18,"column":4}},{"name":"i","generated":{"line":37,"column":22},"source":"Grid.js","original":{"line":18,"column":20}},{"name":"size","generated":{"line":37,"column":26},"source":"Grid.js","original":{"line":18,"column":24}},{"generated":{"line":37,"column":30},"source":"Grid.js","original":{"line":18,"column":4}},{"name":"i","generated":{"line":37,"column":32},"source":"Grid.js","original":{"line":18,"column":30}},{"generated":{"line":37,"column":35},"source":"Grid.js","original":{"line":18,"column":4}},{"generated":{"line":37,"column":37},"source":"Grid.js","original":{"line":18,"column":35}},{"generated":{"line":38,"column":0},"source":"Grid.js","original":{"line":19,"column":6}},{"name":"row","generated":{"line":38,"column":12},"source":"Grid.js","original":{"line":19,"column":12}},{"generated":{"line":38,"column":18},"source":"Grid.js","original":{"line":19,"column":18}},{"generated":{"line":38,"column":20},"source":"Grid.js","original":{"line":19,"column":6}},{"generated":{"line":40,"column":0},"source":"Grid.js","original":{"line":21,"column":6}},{"generated":{"line":40,"column":13},"source":"Grid.js","original":{"line":21,"column":11}},{"name":"j","generated":{"line":40,"column":17},"source":"Grid.js","original":{"line":21,"column":15}},{"generated":{"line":40,"column":21},"source":"Grid.js","original":{"line":21,"column":19}},{"generated":{"line":40,"column":22},"source":"Grid.js","original":{"line":21,"column":6}},{"name":"j","generated":{"line":40,"column":24},"source":"Grid.js","original":{"line":21,"column":22}},{"name":"size","generated":{"line":40,"column":28},"source":"Grid.js","original":{"line":21,"column":26}},{"generated":{"line":40,"column":32},"source":"Grid.js","original":{"line":21,"column":6}},{"name":"j","generated":{"line":40,"column":34},"source":"Grid.js","original":{"line":21,"column":32}},{"generated":{"line":40,"column":37},"source":"Grid.js","original":{"line":21,"column":6}},{"generated":{"line":40,"column":39},"source":"Grid.js","original":{"line":21,"column":37}},{"name":"row","generated":{"line":41,"column":0},"source":"Grid.js","original":{"line":22,"column":8}},{"name":"push","generated":{"line":41,"column":14},"source":"Grid.js","original":{"line":22,"column":12}},{"generated":{"line":41,"column":18},"source":"Grid.js","original":{"line":22,"column":8}},{"name":"Cell","generated":{"line":41,"column":19},"source":"Grid.js","original":{"line":22,"column":17}},{"name":"random","generated":{"line":41,"column":34},"source":"Grid.js","original":{"line":22,"column":22}},{"generated":{"line":41,"column":40},"source":"Grid.js","original":{"line":22,"column":17}},{"generated":{"line":41,"column":42},"source":"Grid.js","original":{"line":22,"column":8}},{"generated":{"line":42,"column":0},"source":"Grid.js","original":{"line":23,"column":7}},{"name":"rows","generated":{"line":44,"column":0},"source":"Grid.js","original":{"line":25,"column":6}},{"name":"push","generated":{"line":44,"column":13},"source":"Grid.js","original":{"line":25,"column":11}},{"generated":{"line":44,"column":17},"source":"Grid.js","original":{"line":25,"column":6}},{"name":"row","generated":{"line":44,"column":18},"source":"Grid.js","original":{"line":25,"column":16}},{"generated":{"line":44,"column":21},"source":"Grid.js","original":{"line":25,"column":6}},{"generated":{"line":45,"column":0},"source":"Grid.js","original":{"line":26,"column":5}},{"generated":{"line":47,"column":0},"source":"Grid.js","original":{"line":28,"column":4}},{"name":"rows","generated":{"line":47,"column":13},"source":"Grid.js","original":{"line":28,"column":11}},{"generated":{"line":47,"column":17},"source":"Grid.js","original":{"line":28,"column":4}},{"generated":{"line":48,"column":0},"source":"Grid.js","original":{"line":29,"column":3}},{"name":"pos","generated":{"line":51,"column":29},"source":"Grid.js","original":{"line":31,"column":11}},{"generated":{"line":51,"column":34},"source":"Grid.js","original":{"line":31,"column":16}},{"generated":{"line":52,"column":0},"source":"Grid.js","original":{"line":32,"column":4}},{"generated":{"line":52,"column":13},"source":"Grid.js","original":{"line":32,"column":11}},{"name":"rows","generated":{"line":52,"column":18},"source":"Grid.js","original":{"line":32,"column":16}},{"generated":{"line":52,"column":22},"source":"Grid.js","original":{"line":32,"column":11}},{"name":"pos","generated":{"line":52,"column":23},"source":"Grid.js","original":{"line":32,"column":21}},{"name":"row","generated":{"line":52,"column":27},"source":"Grid.js","original":{"line":32,"column":25}},{"generated":{"line":52,"column":30},"source":"Grid.js","original":{"line":32,"column":11}},{"name":"pos","generated":{"line":52,"column":32},"source":"Grid.js","original":{"line":32,"column":30}},{"name":"col","generated":{"line":52,"column":36},"source":"Grid.js","original":{"line":32,"column":34}},{"generated":{"line":52,"column":39},"source":"Grid.js","original":{"line":32,"column":11}},{"generated":{"line":52,"column":40},"source":"Grid.js","original":{"line":32,"column":4}},{"generated":{"line":53,"column":0},"source":"Grid.js","original":{"line":33,"column":3}},{"name":"pos","generated":{"line":56,"column":29},"source":"Grid.js","original":{"line":35,"column":11}},{"name":"cell","generated":{"line":56,"column":34},"source":"Grid.js","original":{"line":35,"column":16}},{"generated":{"line":56,"column":40},"source":"Grid.js","original":{"line":35,"column":22}},{"generated":{"line":57,"column":0},"source":"Grid.js","original":{"line":36,"column":4}},{"name":"rows","generated":{"line":57,"column":11},"source":"Grid.js","original":{"line":36,"column":9}},{"generated":{"line":57,"column":15},"source":"Grid.js","original":{"line":36,"column":4}},{"name":"pos","generated":{"line":57,"column":16},"source":"Grid.js","original":{"line":36,"column":14}},{"name":"row","generated":{"line":57,"column":20},"source":"Grid.js","original":{"line":36,"column":18}},{"generated":{"line":57,"column":23},"source":"Grid.js","original":{"line":36,"column":4}},{"name":"pos","generated":{"line":57,"column":25},"source":"Grid.js","original":{"line":36,"column":23}},{"name":"col","generated":{"line":57,"column":29},"source":"Grid.js","original":{"line":36,"column":27}},{"generated":{"line":57,"column":32},"source":"Grid.js","original":{"line":36,"column":4}},{"name":"cell","generated":{"line":57,"column":36},"source":"Grid.js","original":{"line":36,"column":34}},{"generated":{"line":57,"column":40},"source":"Grid.js","original":{"line":36,"column":4}},{"generated":{"line":58,"column":0},"source":"Grid.js","original":{"line":37,"column":3}},{"name":"posOne","generated":{"line":61,"column":30},"source":"Grid.js","original":{"line":39,"column":12}},{"name":"posTwo","generated":{"line":61,"column":38},"source":"Grid.js","original":{"line":39,"column":20}},{"generated":{"line":61,"column":46},"source":"Grid.js","original":{"line":39,"column":28}},{"generated":{"line":62,"column":0},"source":"Grid.js","original":{"line":40,"column":4}},{"name":"cellOne","generated":{"line":62,"column":10},"source":"Grid.js","original":{"line":40,"column":10}},{"generated":{"line":62,"column":20},"source":"Grid.js","original":{"line":40,"column":20}},{"name":"_getCell","generated":{"line":62,"column":25},"source":"Grid.js","original":{"line":40,"column":25}},{"generated":{"line":62,"column":33},"source":"Grid.js","original":{"line":40,"column":20}},{"name":"posOne","generated":{"line":62,"column":34},"source":"Grid.js","original":{"line":40,"column":34}},{"generated":{"line":62,"column":40},"source":"Grid.js","original":{"line":40,"column":20}},{"generated":{"line":62,"column":41},"source":"Grid.js","original":{"line":40,"column":4}},{"generated":{"line":63,"column":0},"source":"Grid.js","original":{"line":41,"column":4}},{"name":"_setCell","generated":{"line":63,"column":11},"source":"Grid.js","original":{"line":41,"column":9}},{"generated":{"line":63,"column":19},"source":"Grid.js","original":{"line":41,"column":4}},{"name":"posOne","generated":{"line":63,"column":20},"source":"Grid.js","original":{"line":41,"column":18}},{"generated":{"line":63,"column":26},"source":"Grid.js","original":{"line":41,"column":4}},{"generated":{"line":63,"column":28},"source":"Grid.js","original":{"line":41,"column":26}},{"name":"_getCell","generated":{"line":63,"column":33},"source":"Grid.js","original":{"line":41,"column":31}},{"generated":{"line":63,"column":41},"source":"Grid.js","original":{"line":41,"column":26}},{"name":"posTwo","generated":{"line":63,"column":42},"source":"Grid.js","original":{"line":41,"column":40}},{"generated":{"line":63,"column":48},"source":"Grid.js","original":{"line":41,"column":26}},{"generated":{"line":63,"column":49},"source":"Grid.js","original":{"line":41,"column":4}},{"generated":{"line":64,"column":0},"source":"Grid.js","original":{"line":42,"column":4}},{"name":"_setCell","generated":{"line":64,"column":11},"source":"Grid.js","original":{"line":42,"column":9}},{"generated":{"line":64,"column":19},"source":"Grid.js","original":{"line":42,"column":4}},{"name":"posTwo","generated":{"line":64,"column":20},"source":"Grid.js","original":{"line":42,"column":18}},{"generated":{"line":64,"column":26},"source":"Grid.js","original":{"line":42,"column":4}},{"name":"cellOne","generated":{"line":64,"column":28},"source":"Grid.js","original":{"line":42,"column":26}},{"generated":{"line":64,"column":35},"source":"Grid.js","original":{"line":42,"column":4}},{"generated":{"line":65,"column":0},"source":"Grid.js","original":{"line":43,"column":3}},{"generated":{"line":68,"column":28},"source":"Grid.js","original":{"line":45,"column":10}},{"generated":{"line":69,"column":0},"source":"Grid.js","original":{"line":46,"column":4}},{"name":"gridEl","generated":{"line":69,"column":10},"source":"Grid.js","original":{"line":46,"column":10}},{"name":"document","generated":{"line":69,"column":19},"source":"Grid.js","original":{"line":46,"column":19}},{"name":"createElement","generated":{"line":69,"column":28},"source":"Grid.js","original":{"line":46,"column":28}},{"generated":{"line":69,"column":41},"source":"Grid.js","original":{"line":46,"column":19}},{"generated":{"line":69,"column":42},"source":"Grid.js","original":{"line":46,"column":42}},{"generated":{"line":69,"column":47},"source":"Grid.js","original":{"line":46,"column":19}},{"generated":{"line":69,"column":48},"source":"Grid.js","original":{"line":46,"column":4}},{"name":"gridEl","generated":{"line":70,"column":0},"source":"Grid.js","original":{"line":47,"column":4}},{"name":"classList","generated":{"line":70,"column":13},"source":"Grid.js","original":{"line":47,"column":11}},{"generated":{"line":70,"column":22},"source":"Grid.js","original":{"line":47,"column":4}},{"name":"add","generated":{"line":70,"column":23},"source":"Grid.js","original":{"line":47,"column":21}},{"generated":{"line":70,"column":26},"source":"Grid.js","original":{"line":47,"column":4}},{"generated":{"line":70,"column":27},"source":"Grid.js","original":{"line":47,"column":25}},{"generated":{"line":70,"column":33},"source":"Grid.js","original":{"line":47,"column":4}},{"generated":{"line":72,"column":0},"source":"Grid.js","original":{"line":49,"column":4}},{"name":"rows","generated":{"line":72,"column":11},"source":"Grid.js","original":{"line":49,"column":9}},{"generated":{"line":72,"column":15},"source":"Grid.js","original":{"line":49,"column":4}},{"name":"forEach","generated":{"line":72,"column":16},"source":"Grid.js","original":{"line":49,"column":14}},{"generated":{"line":72,"column":23},"source":"Grid.js","original":{"line":49,"column":4}},{"generated":{"line":72,"column":24},"source":"Grid.js","original":{"line":49,"column":22}},{"generated":{"line":72,"column":39},"source":"Grid.js","original":{"line":49,"column":29}},{"generated":{"line":73,"column":0},"source":"Grid.js","original":{"line":50,"column":6}},{"name":"rowEl","generated":{"line":73,"column":12},"source":"Grid.js","original":{"line":50,"column":12}},{"name":"document","generated":{"line":73,"column":20},"source":"Grid.js","original":{"line":50,"column":20}},{"name":"createElement","generated":{"line":73,"column":29},"source":"Grid.js","original":{"line":50,"column":29}},{"generated":{"line":73,"column":42},"source":"Grid.js","original":{"line":50,"column":20}},{"generated":{"line":73,"column":43},"source":"Grid.js","original":{"line":50,"column":43}},{"generated":{"line":73,"column":48},"source":"Grid.js","original":{"line":50,"column":20}},{"generated":{"line":73,"column":49},"source":"Grid.js","original":{"line":50,"column":6}},{"name":"rowEl","generated":{"line":74,"column":0},"source":"Grid.js","original":{"line":51,"column":6}},{"name":"classList","generated":{"line":74,"column":14},"source":"Grid.js","original":{"line":51,"column":12}},{"generated":{"line":74,"column":23},"source":"Grid.js","original":{"line":51,"column":6}},{"name":"add","generated":{"line":74,"column":24},"source":"Grid.js","original":{"line":51,"column":22}},{"generated":{"line":74,"column":27},"source":"Grid.js","original":{"line":51,"column":6}},{"generated":{"line":74,"column":28},"source":"Grid.js","original":{"line":51,"column":26}},{"generated":{"line":74,"column":33},"source":"Grid.js","original":{"line":51,"column":6}},{"name":"row","generated":{"line":76,"column":0},"source":"Grid.js","original":{"line":53,"column":6}},{"name":"forEach","generated":{"line":76,"column":12},"source":"Grid.js","original":{"line":53,"column":10}},{"generated":{"line":76,"column":19},"source":"Grid.js","original":{"line":53,"column":6}},{"generated":{"line":76,"column":20},"source":"Grid.js","original":{"line":53,"column":18}},{"generated":{"line":76,"column":36},"source":"Grid.js","original":{"line":53,"column":26}},{"name":"rowEl","generated":{"line":77,"column":0},"source":"Grid.js","original":{"line":54,"column":8}},{"name":"appendChild","generated":{"line":77,"column":16},"source":"Grid.js","original":{"line":54,"column":14}},{"generated":{"line":77,"column":27},"source":"Grid.js","original":{"line":54,"column":8}},{"name":"cell","generated":{"line":77,"column":28},"source":"Grid.js","original":{"line":54,"column":26}},{"name":"getEl","generated":{"line":77,"column":33},"source":"Grid.js","original":{"line":54,"column":31}},{"generated":{"line":77,"column":38},"source":"Grid.js","original":{"line":54,"column":26}},{"generated":{"line":77,"column":40},"source":"Grid.js","original":{"line":54,"column":8}},{"generated":{"line":78,"column":0},"source":"Grid.js","original":{"line":55,"column":7}},{"generated":{"line":78,"column":9},"source":"Grid.js","original":{"line":53,"column":6}},{"name":"gridEl","generated":{"line":80,"column":0},"source":"Grid.js","original":{"line":57,"column":6}},{"name":"appendChild","generated":{"line":80,"column":15},"source":"Grid.js","original":{"line":57,"column":13}},{"generated":{"line":80,"column":26},"source":"Grid.js","original":{"line":57,"column":6}},{"name":"rowEl","generated":{"line":80,"column":27},"source":"Grid.js","original":{"line":57,"column":25}},{"generated":{"line":80,"column":32},"source":"Grid.js","original":{"line":57,"column":6}},{"generated":{"line":81,"column":0},"source":"Grid.js","original":{"line":58,"column":5}},{"generated":{"line":81,"column":7},"source":"Grid.js","original":{"line":49,"column":4}},{"generated":{"line":83,"column":0},"source":"Grid.js","original":{"line":60,"column":4}},{"name":"gridEl","generated":{"line":83,"column":13},"source":"Grid.js","original":{"line":60,"column":11}},{"generated":{"line":83,"column":19},"source":"Grid.js","original":{"line":60,"column":4}},{"generated":{"line":84,"column":0},"source":"Grid.js","original":{"line":61,"column":3}},{"name":"Grid","generated":{"line":90,"column":18},"source":"Grid.js","original":{"line":64,"column":15}}],"sources":{"Grid.js":"import { BOARD_SIZE } from './constants'\n\nimport Cell from './Cell'\n\nclass Grid {\n  constructor() {\n    this.rows = this._buildRows(BOARD_SIZE);\n    this.el = this._buildEl()\n  }\n\n  _buildEl() {\n    const el = document.createElement('div')\n  }\n\n  _buildRows(size) {\n    const rows = [];\n\n    for (let i = 0; i < size; i++) {\n      const row = [];\n\n      for (let j = 0; j < size; j++) {\n        row.push(Cell.random());\n      }\n\n      rows.push(row);\n    }\n\n    return rows;\n  }\n\n  _getCell(pos) {\n    return this.rows[pos.row][pos.col];\n  }\n\n  _setCell(pos, cell) {\n    this.rows[pos.row][pos.col] = cell;\n  }\n\n  swapCells(posOne, posTwo) {\n    const cellOne = this._getCell(posOne);\n    this._setCell(posOne, this._getCell(posTwo));\n    this._setCell(posTwo, cellOne);\n  }\n\n  getEl() {\n    const gridEl = document.createElement('div');\n    gridEl.classList.add('grid');\n\n    this.rows.forEach(row => {\n      const rowEl = document.createElement('div');\n      rowEl.classList.add('row');\n\n      row.forEach(cell => {\n        rowEl.appendChild(cell.getEl());\n      })\n\n      gridEl.appendChild(rowEl);\n    })\n\n    return gridEl;\n  }\n}\n\nexport default Grid;"},"lineCount":null}},"hash":"05f764bfced94e988a904d61b9ed37f6","cacheData":{"env":{}}}